{
  "version": 2.0,
  "questions": [
    {
      "question": "___________ is employed to achieve reliable transport in TCP. ",
      "answers": {
        "a": "Packet",
        "b": "Buffer",
        "c": " Segment",
        "d": "Acknowledgment"
      },
       
      "correctAnswer": "d",
      "difficulty": "beginner"
    },
    {
      "question": "Consider a TCP connection sending a file of 34569 bytes. The first byte is numbered 57899. What is the segment's sequence number if all data is sent in only one segment? ",
      "answers": {
        "a": "57900",
        "b": "57899",
        "c": "57898",
        "d": "57991"
      },
      
      "correctAnswer": "b",
      "difficulty": "beginner"
    },
    {
      "question": "The size of the acknowledgement number in a TCP header is _____.",
      "answers": {
        "a": "32 bits",
        "b": "16 bits",
        "c": "24 bits",
        "d": "1 byte"
      },
     
      "correctAnswer": "a",
      "difficulty": "beginner"
    }
  ]
}
